[{"id":346,"title":"Раздоры II","image":"images/346.jpg","tags":["недвижимость","промо","greencow"],"url":"https://razdory2.ru/","date":1541498449,"edit_date":1582923529,"isHighlighted":false,"isRemoved":false,"slugs":["nedvizhimost","promo","greencow"]},{"id":340,"title":"Barkli Gallery","image":"images/340.jpg","tags":["недвижимость","промо","greencow"],"url":"http://barkligallery.ru","date":1540980017,"edit_date":1582923529,"isHighlighted":false,"isRemoved":false,"slugs":["nedvizhimost","promo","greencow"]}]