[{"id":647,"title":"АВТОМОБИЛЬ!","image":"images/647.jpg","tags":["финансы","банк","промо","рокетбанк"],"url":"https://tesla.rocketbank.ru/","date":1577440805,"edit_date":1582914607,"isHighlighted":false,"isRemoved":false},{"id":621,"title":"Bank UA","image":"images/621.jpg","tags":["медиа","финансы","инвестиции","hexagon"],"url":"https://bank.ua/","date":1573207269,"edit_date":1582912125,"isHighlighted":false,"isRemoved":false},{"id":573,"title":"Справочная","image":"images/573.jpg","tags":["блог","финансы","банк"],"url":"https://allo.tochka.com/","date":1566381674,"edit_date":1582912124,"isHighlighted":false,"isRemoved":false},{"id":429,"title":"БКС Банк","image":"images/429.jpg","tags":["финансы","банк","aic"],"url":"https://beta.bcs-bank.com/","date":1549360822,"edit_date":1582917395,"isHighlighted":false,"isRemoved":false}]