[{"id":244,"title":"Фламп","image":"images/244.jpg","tags":["сервис","сообщество"],"url":"https://flamp.ru/","date":1532253616,"edit_date":1582923805,"isHighlighted":false,"isRemoved":false},{"id":243,"title":"Кинопоиск Онлайн","image":"images/243.jpg","tags":["сервис","кино","кинопоиск"],"url":"https://www.kinopoisk.ru/watch/films/","date":1532167221,"edit_date":1582966524,"isHighlighted":true,"isRemoved":false},{"id":223,"title":"Советские фильмы на английском языке","image":"images/223.jpg","tags":["сервис","кино"],"url":"https://sovietmoviesonline.com/ru/","date":1530439218,"edit_date":1582923805,"isHighlighted":false,"isRemoved":false},{"id":222,"title":"Яндекс.Касса","image":"images/222.jpg","tags":["финансы","бизнес","сервис"],"url":"https://kassa.yandex.ru/","date":1530352817,"edit_date":1582923805,"isHighlighted":false,"isRemoved":false},{"id":220,"title":"Fins","image":"images/220.jpg","tags":["финансы","сервис","бкс"],"url":"https://fins.money/","date":1530180010,"edit_date":1582923805,"isHighlighted":false,"isRemoved":false},{"id":218,"title":"ДомКлик","image":"images/218.jpg","tags":["недвижимость","сервис","сбербанк"],"url":"https://domclick.ru/","date":1530007224,"edit_date":1582923805,"isHighlighted":false,"isRemoved":false},{"id":202,"title":"RealtimeBoard","image":"images/202.jpg","tags":["сервис"],"url":"https://realtimeboard.com/ru/","date":1528624801,"edit_date":1582966580,"isHighlighted":true,"isRemoved":false},{"id":199,"title":"Bookmate","image":"images/199.jpg","tags":["сервис"],"url":"https://ru.bookmate.com/","date":1528365608,"edit_date":1582924492,"isHighlighted":false,"isRemoved":false},{"id":195,"title":"FRUIT UP","image":"images/195.jpg","tags":["сервис","доставка","еда"],"url":"http://www.fruitup.ru/","date":1528020007,"edit_date":1582924492,"isHighlighted":false,"isRemoved":false},{"id":193,"title":"Сделано","image":"images/193.jpg","tags":["услуги","сервис","конструктор"],"url":"https://sdelano.ru/","date":1527933601,"edit_date":1582966589,"isHighlighted":true,"isRemoved":false},{"id":189,"title":"Яндекс Плюс","image":"images/189.jpg","tags":["сервис","услуги","промо"],"url":"https://plus.yandex.ru","date":1527581050,"edit_date":1582924492,"isHighlighted":false,"isRemoved":false},{"id":186,"title":"Comepay","image":"images/186.jpg","tags":["финансы","сервис"],"url":"https://comepay.ru/","date":1527328811,"edit_date":1582924492,"isHighlighted":false,"isRemoved":false},{"id":181,"title":"Setka Workflow","image":"images/181.jpg","tags":["сервис","услуги","setka"],"url":"https://setka.io/ru/workflow/","date":1526896811,"edit_date":1582966695,"isHighlighted":true,"isRemoved":false},{"id":167,"title":"Wepster","image":"images/167.jpg","tags":["сервис","услуги","промо"],"url":"http://wepster.com/","date":1525687216,"edit_date":1582924492,"isHighlighted":false,"isRemoved":false},{"id":147,"title":"BlaBlaCar","image":"images/147.jpg","tags":["услуги","сервис","путешествия"],"url":"https://www.blablacar.ru/","date":1523786415,"edit_date":1582924492,"isHighlighted":false,"isRemoved":false},{"id":143,"title":"Qlean","image":"images/143.jpg","tags":["услуги","сервис"],"url":"https://qlean.ru/","date":1523440806,"edit_date":1582924492,"isHighlighted":false,"isRemoved":false},{"id":137,"title":"Школьные Знания","image":"images/137.jpg","tags":["образование","сервис"],"url":"https://znanija.com/","date":1523008812,"edit_date":1582924492,"isHighlighted":false,"isRemoved":false},{"id":101,"title":"Юла","image":"images/101.jpg","tags":["сервис","доскаобъявлений","mailru"],"url":"https://youla.io/","date":1519984817,"edit_date":1582924491,"isHighlighted":false,"isRemoved":false}]