[
  {
    "id": 186,
    "title": "Comepay",
    "image": "data/images/186.jpg",
    "tags": [
      "финансы",
      "сервис"
    ],
    "url": "https://comepay.ru/",
    "date": 1527328811,
    "edit_date": 1583185536,
    "isHighlighted": false,
    "isRemoved": false,
    "slugs": [
      "finansi",
      "servis"
    ],
    "awards": []
  },
  {
    "id": 185,
    "title": "EMKA",
    "image": "data/images/185.jpg",
    "tags": [
      "производство",
      "магазин",
      "одежда",
      "мода",
      "icrea"
    ],
    "url": "https://www.emkafashion.ru/",
    "date": 1527242423,
    "edit_date": 1583185536,
    "isHighlighted": false,
    "isRemoved": false,
    "slugs": [
      "proizvodstvo",
      "magazin",
      "odezhda",
      "moda",
      "icrea"
    ],
    "awards": []
  },
  {
    "id": 184,
    "title": "Zero",
    "caption": "Zero\nhttp://zero.ru/\n\n#студия #портфолио #услуги #агентство",
    "image": "data/images/184.jpg",
    "tags": [
      "студия",
      "портфолио",
      "услуги",
      "агентство"
    ],
    "url": "http://zero.ru/",
    "date": 1527156014,
    "edit_date": 1583389420,
    "isHighlighted": false,
    "isRemoved": false,
    "slugs": [
      "studiya",
      "portfolio",
      "uslugi",
      "agentstvo"
    ],
    "awards": []
  },
  {
    "id": 183,
    "title": "ThisIsMedia",
    "image": "data/images/183.jpg",
    "tags": [
      "медиа",
      "журнал"
    ],
    "url": "https://thisis.media/",
    "date": 1527069606,
    "edit_date": 1583185536,
    "isHighlighted": false,
    "isRemoved": false,
    "slugs": [
      "media",
      "zhurnal"
    ],
    "awards": []
  },
  {
    "id": 182,
    "title": "Беру",
    "image": "data/images/182.jpg",
    "tags": [
      "магазин",
      "маркетплейс",
      "яндекс"
    ],
    "url": "https://beru.ru/",
    "date": 1526983229,
    "edit_date": 1583185536,
    "isHighlighted": false,
    "isRemoved": false,
    "slugs": [
      "magazin",
      "marketpleis",
      "yandeks"
    ],
    "awards": []
  },
  {
    "id": 181,
    "title": "Setka Workflow",
    "image": "data/images/181.jpg",
    "tags": [
      "сервис",
      "услуги",
      "setka"
    ],
    "url": "https://setka.io/ru/workflow/",
    "date": 1526896811,
    "edit_date": 1583185536,
    "isHighlighted": true,
    "isRemoved": false,
    "slugs": [
      "servis",
      "uslugi",
      "setka"
    ],
    "awards": []
  },
  {
    "id": 180,
    "title": "MODI",
    "image": "data/images/180.jpg",
    "tags": [
      "магазин",
      "hellobarty"
    ],
    "url": "https://modi.ru/",
    "date": 1526810420,
    "edit_date": 1583185536,
    "isHighlighted": false,
    "isRemoved": false,
    "slugs": [
      "magazin",
      "hellobarty"
    ],
    "awards": []
  },
  {
    "id": 179,
    "title": "Телеграф",
    "image": "data/images/179.jpg",
    "tags": [
      "журнал",
      "образование",
      "люди",
      "the23"
    ],
    "url": "http://telegraf.design/",
    "date": 1526724012,
    "edit_date": 1583185536,
    "isHighlighted": false,
    "isRemoved": false,
    "slugs": [
      "zhurnal",
      "obrazovanie",
      "lyudi",
      "the23"
    ],
    "awards": []
  },
  {
    "id": 178,
    "title": "Lamp In Room",
    "image": "data/images/178.jpg",
    "tags": [
      "магазин",
      "braind"
    ],
    "url": "https://www.lampinroom.ru/",
    "date": 1526637607,
    "edit_date": 1583185536,
    "isHighlighted": false,
    "isRemoved": false,
    "slugs": [
      "magazin",
      "braind"
    ],
    "awards": []
  },
  {
    "id": 177,
    "title": "Детская клиническая больница",
    "image": "data/images/177.jpg",
    "tags": [
      "медицина",
      "здоровье",
      "aic"
    ],
    "url": "http://deti-sechenov.ru/",
    "date": 1526551212,
    "edit_date": 1583185536,
    "isHighlighted": false,
    "isRemoved": false,
    "slugs": [
      "meditsina",
      "zdorove",
      "aic"
    ],
    "awards": []
  },
  {
    "id": 176,
    "title": "re:market",
    "image": "data/images/176.jpg",
    "tags": [
      "магазин"
    ],
    "url": "http://remarket-shop.ru/",
    "date": 1526464806,
    "edit_date": 1583185536,
    "isHighlighted": false,
    "isRemoved": false,
    "slugs": [
      "magazin"
    ],
    "awards": []
  },
  {
    "id": 175,
    "title": "Ладожская Усадьба",
    "image": "data/images/175.jpg",
    "tags": [
      "букинг",
      "услуги",
      "развлечения",
      "cloudmill"
    ],
    "url": "http://ladoga.hellem.ru/",
    "date": 1526378415,
    "edit_date": 1583185536,
    "isHighlighted": false,
    "isRemoved": false,
    "slugs": [
      "buking",
      "uslugi",
      "razvlecheniya",
      "cloudmill"
    ],
    "awards": []
  },
  {
    "id": 174,
    "title": "РОСГОССТРАХ БАНК",
    "image": "data/images/174.jpg",
    "tags": [
      "банк",
      "финансы",
      "aic"
    ],
    "url": "https://www.rgsbank.ru/",
    "date": 1526292021,
    "edit_date": 1583185536,
    "isHighlighted": false,
    "isRemoved": false,
    "slugs": [
      "bank",
      "finansi",
      "aic"
    ],
    "awards": []
  },
  {
    "id": 173,
    "title": "Хайтек",
    "image": "data/images/173.jpg",
    "tags": [
      "медиа",
      "новости",
      "технологии"
    ],
    "url": "https://hightech.fm/",
    "date": 1526205609,
    "edit_date": 1583185536,
    "isHighlighted": false,
    "isRemoved": false,
    "slugs": [
      "media",
      "novosti",
      "tekhnologii"
    ],
    "awards": []
  },
  {
    "id": 172,
    "title": "re:Store",
    "image": "data/images/172.jpg",
    "tags": [
      "магазин"
    ],
    "url": "https://www.re-store.ru/",
    "date": 1526119218,
    "edit_date": 1583185536,
    "isHighlighted": false,
    "isRemoved": false,
    "slugs": [
      "magazin"
    ],
    "awards": []
  },
  {
    "id": 171,
    "title": "Legacy",
    "image": "data/images/171.jpg",
    "tags": [
      "фонд",
      "бизнес",
      "финансы",
      "сибирикс"
    ],
    "url": "http://legacy-ef.com/",
    "date": 1526032809,
    "edit_date": 1583185536,
    "isHighlighted": false,
    "isRemoved": false,
    "slugs": [
      "fond",
      "biznes",
      "finansi",
      "sibiriks"
    ],
    "awards": []
  },
  {
    "id": 170,
    "title": "HANDWERS",
    "image": "data/images/170.jpg",
    "tags": [
      "магазин",
      "доставка"
    ],
    "url": "https://handwers.com/ru/",
    "date": 1525946421,
    "edit_date": 1583185536,
    "isHighlighted": false,
    "isRemoved": false,
    "slugs": [
      "magazin",
      "dostavka"
    ],
    "awards": []
  },
  {
    "id": 169,
    "title": "Администрация Кемеровской области",
    "image": "data/images/169.jpg",
    "tags": [
      "государство",
      "медиа",
      "россия"
    ],
    "url": "https://ako.ru/",
    "date": 1525860009,
    "edit_date": 1583185536,
    "isHighlighted": false,
    "isRemoved": false,
    "slugs": [
      "gosudarstvo",
      "media",
      "rossiya"
    ],
    "awards": []
  },
  {
    "id": 168,
    "title": "АВ Экспресс",
    "image": "data/images/168.jpg",
    "tags": [
      "магазин",
      "доставка",
      "aic"
    ],
    "url": "https://express.av.ru/",
    "date": 1525773610,
    "edit_date": 1583185536,
    "isHighlighted": false,
    "isRemoved": false,
    "slugs": [
      "magazin",
      "dostavka",
      "aic"
    ],
    "awards": []
  },
  {
    "id": 167,
    "title": "Wepster",
    "image": "data/images/167.jpg",
    "tags": [
      "сервис",
      "услуги",
      "промо"
    ],
    "url": "http://wepster.com/",
    "date": 1525687216,
    "edit_date": 1583185536,
    "isHighlighted": false,
    "isRemoved": false,
    "slugs": [
      "servis",
      "uslugi",
      "promo"
    ],
    "awards": []
  }
]