[
  {
    "id": 1000,
    "title": "BoldItalic",
    "caption": "BoldItalic\nhttps://bolditalic.type.school\n\n#образование #мероприятие #tilda #дмитрийопалев\nСпасибо за ссылку @masterlobster",
    "image": "data/images/1000.jpg",
    "tags": [
      "образование",
      "мероприятие",
      "tilda",
      "дмитрийопалев"
    ],
    "url": "https://bolditalic.type.school",
    "date": 1632305878,
    "isMonth": false,
    "isYear": false,
    "isHighlighted": false,
    "isRemoved": false,
    "slugs": [
      "obrazovanie",
      "meropriyatie",
      "tilda",
      "dmitriiopalev"
    ],
    "awards": []
  },
  {
    "id": 999,
    "title": "Фонд А.Козлова",
    "caption": "Фонд А.Козлова\nhttps://www.kozlov.fund/\n\n#благотворительность #фонд #музыка #webflow #methodzero\nСпасибо за ссылку @boris_zagor",
    "image": "data/images/999.jpg",
    "tags": [
      "благотворительность",
      "фонд",
      "музыка",
      "webflow",
      "methodzero"
    ],
    "url": "https://www.kozlov.fund/",
    "date": 1632141956,
    "edit_date": 1632142023,
    "isMonth": false,
    "isYear": false,
    "isHighlighted": false,
    "isRemoved": false,
    "slugs": [
      "blagotvoritelnost",
      "fond",
      "muzika",
      "webflow",
      "methodzero"
    ],
    "awards": []
  },
  {
    "id": 998,
    "title": "Хроника Музея современного искусства «Гараж»",
    "caption": "Хроника Музея современного искусства «Гараж»\nhttps://chronicle.garagemca.org/\n\n#спецпроект #история #павелкедич",
    "image": "data/images/998.jpg",
    "tags": [
      "спецпроект",
      "история",
      "павелкедич"
    ],
    "url": "https://chronicle.garagemca.org/",
    "date": 1631973323,
    "edit_date": 1631973397,
    "isMonth": false,
    "isYear": false,
    "isHighlighted": false,
    "isRemoved": false,
    "slugs": [
      "spetsproekt",
      "istoriya",
      "pavelkedich"
    ],
    "awards": []
  },
  {
    "id": 997,
    "title": "М-464: нераспознаваемая индивидуальность",
    "caption": "М-464: нераспознаваемая индивидуальность\nhttps://m464.leta.today/\n\n#спецпроект #readymag #павелкедич\nСпасибо за ссылку @readymag_official",
    "image": "data/images/997.jpg",
    "tags": [
      "спецпроект",
      "readymag",
      "павелкедич"
    ],
    "url": "https://m464.leta.today/",
    "date": 1631884136,
    "isMonth": false,
    "isYear": false,
    "isHighlighted": false,
    "isRemoved": false,
    "slugs": [
      "spetsproekt",
      "readymag",
      "pavelkedich"
    ],
    "awards": []
  },
  {
    "id": 996,
    "title": "Tuman Studio",
    "caption": "Tuman Studio\nhttps://tumanstudio.com/ru\n\n#портфолио #студия",
    "image": "data/images/996.jpg",
    "tags": [
      "портфолио",
      "студия"
    ],
    "url": "https://tumanstudio.com/ru",
    "date": 1631775373,
    "isMonth": false,
    "isYear": false,
    "isHighlighted": false,
    "isRemoved": false,
    "slugs": [
      "portfolio",
      "studiya"
    ],
    "awards": []
  },
  {
    "id": 994,
    "title": "Noôdome",
    "caption": "Noôdome\nhttps://noodome.club/\n\n#сервис #бизнес #мероприятие #люди #whiterussianstudio\nСпасибо за ссылку @tim_or_timofey",
    "image": "data/images/994.jpg",
    "tags": [
      "сервис",
      "бизнес",
      "мероприятие",
      "люди",
      "whiterussianstudio"
    ],
    "url": "https://noodome.club/",
    "date": 1631732716,
    "edit_date": 1631732814,
    "isMonth": false,
    "isYear": false,
    "isHighlighted": false,
    "isRemoved": false,
    "slugs": [
      "servis",
      "biznes",
      "meropriyatie",
      "lyudi",
      "whiterussianstudio"
    ],
    "awards": []
  },
  {
    "id": 993,
    "title": "Charmer Design Unit",
    "caption": "Charmer Design Unit\nhttps://russian.charmer.design/\n\n#портфолио #услуги #readymag\nСпасибо за ссылку @masterlobster",
    "image": "data/images/993.jpg",
    "tags": [
      "портфолио",
      "услуги",
      "readymag"
    ],
    "url": "https://russian.charmer.design/",
    "date": 1631562073,
    "edit_date": 1631562247,
    "isMonth": false,
    "isYear": false,
    "isHighlighted": false,
    "isRemoved": false,
    "slugs": [
      "portfolio",
      "uslugi",
      "readymag"
    ],
    "awards": []
  },
  {
    "id": 992,
    "title": "Кукушка",
    "caption": "Кукушка\nhttps://coocooschool.ru/\n\n#образование #readymag\nСпасибо за ссылку @tim_or_timofey",
    "image": "data/images/992.jpg",
    "tags": [
      "образование",
      "readymag"
    ],
    "url": "https://coocooschool.ru/",
    "date": 1631536201,
    "isMonth": false,
    "isYear": false,
    "isHighlighted": false,
    "isRemoved": false,
    "slugs": [
      "obrazovanie",
      "readymag"
    ],
    "awards": []
  },
  {
    "id": 991,
    "title": "Много Лосося",
    "caption": "Много Лосося\nhttps://mnogolososya.ru/\n\n#промо #приложение #еда #доставка #whiterussianstudio\nСпасибо за ссылку @winkeyless",
    "image": "data/images/991.jpg",
    "tags": [
      "промо",
      "приложение",
      "еда",
      "доставка",
      "whiterussianstudio"
    ],
    "url": "https://mnogolososya.ru/",
    "date": 1631257206,
    "isMonth": false,
    "isYear": false,
    "isHighlighted": false,
    "isRemoved": false,
    "slugs": [
      "promo",
      "prilozhenie",
      "yeda",
      "dostavka",
      "whiterussianstudio"
    ],
    "awards": []
  },
  {
    "id": 990,
    "title": "Fintech Design Conf",
    "caption": "Fintech Design Conf\nhttps://www.fintechdesign.ru/\n\n#мероприятие #финансы #банк",
    "image": "data/images/990.jpg",
    "tags": [
      "мероприятие",
      "финансы",
      "банк"
    ],
    "url": "https://www.fintechdesign.ru/",
    "date": 1631212254,
    "isMonth": false,
    "isYear": false,
    "isHighlighted": false,
    "isRemoved": false,
    "slugs": [
      "meropriyatie",
      "finansi",
      "bank"
    ],
    "awards": []
  },
  {
    "id": 989,
    "title": "Готово",
    "caption": "Готово\nhttps://gotovokitchen.ru/\n\n#сервис #доставка #еда #приложение",
    "image": "data/images/989.jpg",
    "tags": [
      "сервис",
      "доставка",
      "еда",
      "приложение"
    ],
    "url": "https://gotovokitchen.ru/",
    "date": 1630915246,
    "isMonth": false,
    "isYear": false,
    "isHighlighted": false,
    "isRemoved": false,
    "slugs": [
      "servis",
      "dostavka",
      "yeda",
      "prilozhenie"
    ],
    "awards": []
  },
  {
    "id": 988,
    "title": "Годовой отчет Фонда Amway",
    "caption": "Годовой отчет Фонда Amway\nhttps://www.amwayreport2020.ru/\n\n#благотворительность #отчет #webflow #redis\nСпасибо за ссылку @badgoodgrll",
    "image": "data/images/988.jpg",
    "tags": [
      "благотворительность",
      "отчет",
      "webflow",
      "redis"
    ],
    "url": "https://www.amwayreport2020.ru/",
    "date": 1630654736,
    "isMonth": false,
    "isYear": false,
    "isHighlighted": false,
    "isRemoved": false,
    "slugs": [
      "blagotvoritelnost",
      "otchet",
      "webflow",
      "redis"
    ],
    "awards": []
  },
  {
    "id": 986,
    "title": "Круглосуточная ветеринарная клиника Vet City",
    "caption": "Круглосуточная ветеринарная клиника Vet City\nhttps://vet.city/\n\n#промо #услуги #животные #skam\nСпасибо за ссылку @secretd",
    "image": "data/images/986.jpg",
    "tags": [
      "промо",
      "услуги",
      "животные",
      "skam"
    ],
    "url": "https://vet.city/",
    "date": 1630494257,
    "isMonth": false,
    "isYear": false,
    "isHighlighted": false,
    "isRemoved": false,
    "slugs": [
      "promo",
      "uslugi",
      "zhivotnie",
      "skam"
    ],
    "awards": []
  },
  {
    "id": 985,
    "title": "Maxim Stolar",
    "caption": "Maxim Stolar\nhttps://readymag.com/maxstolar/works/\n\n#портфолио #readymag\nСпасибо за ссылку @readymag_official",
    "image": "data/images/985.jpg",
    "tags": [
      "портфолио",
      "readymag"
    ],
    "url": "https://readymag.com/maxstolar/works/",
    "date": 1629820159,
    "isMonth": false,
    "isYear": false,
    "isHighlighted": false,
    "isRemoved": false,
    "slugs": [
      "portfolio",
      "readymag"
    ],
    "awards": []
  },
  {
    "id": 984,
    "title": "Агентство комплексного интернет-маркетинга Wemakefab",
    "caption": "Агентство комплексного интернет-маркетинга Wemakefab\nhttps://wemakefab.ru/\n\n#портфолио #агентство  #lagutalaguta\nСпасибо за ссылку @masterlobster",
    "image": "data/images/984.jpg",
    "tags": [
      "портфолио",
      "агентство",
      "lagutalaguta"
    ],
    "url": "https://wemakefab.ru/",
    "date": 1629624600,
    "isMonth": false,
    "isYear": false,
    "isHighlighted": false,
    "isRemoved": false,
    "slugs": [
      "portfolio",
      "agentstvo",
      "lagutalaguta"
    ],
    "awards": []
  },
  {
    "id": 983,
    "title": "Дом устаревших проектов",
    "caption": "Дом устаревших проектов\nhttps://belpromproekt.leta.today/\n\n#спецпроект #readymag #павелкедич",
    "image": "data/images/983.jpg",
    "tags": [
      "спецпроект",
      "readymag",
      "павелкедич"
    ],
    "url": "https://belpromproekt.leta.today/",
    "date": 1629378373,
    "edit_date": 1629378387,
    "isMonth": false,
    "isYear": false,
    "isHighlighted": false,
    "isRemoved": false,
    "slugs": [
      "spetsproekt",
      "readymag",
      "pavelkedich"
    ],
    "awards": []
  },
  {
    "id": 982,
    "title": "Команда цифрового дизайна PRAGMATICA",
    "caption": "Команда цифрового дизайна PRAGMATICA\nhttps://pragmatica.design/\n\n#портфолио #студия #readymag\nСпасибо за ссылку @censor_online",
    "image": "data/images/982.jpg",
    "tags": [
      "портфолио",
      "студия",
      "readymag"
    ],
    "url": "https://pragmatica.design/",
    "date": 1629227756,
    "isMonth": false,
    "isYear": false,
    "isHighlighted": false,
    "isRemoved": false,
    "slugs": [
      "portfolio",
      "studiya",
      "readymag"
    ],
    "awards": []
  },
  {
    "id": 981,
    "title": "Не надо стесняться",
    "caption": "Не надо стесняться\nhttps://nns.i-m-i.ru/\n\n #спецпроект #музыка #ими\nСпасибо за ссылку @AndyAbramov",
    "image": "data/images/981.jpg",
    "tags": [
      "спецпроект",
      "музыка",
      "ими"
    ],
    "url": "https://nns.i-m-i.ru/",
    "date": 1628943569,
    "isMonth": false,
    "isYear": false,
    "isHighlighted": false,
    "isRemoved": false,
    "slugs": [
      "spetsproekt",
      "muzika",
      "imi"
    ],
    "awards": []
  },
  {
    "id": 980,
    "title": "Создавайте Финтех с нуля",
    "caption": "Создавайте Финтех с нуля\nhttps://yandexfintech.ru/\n\n#hr #работа #яндекс #whiterussianstudio",
    "image": "data/images/980.jpg",
    "tags": [
      "hr",
      "работа",
      "яндекс",
      "whiterussianstudio"
    ],
    "url": "https://yandexfintech.ru/",
    "date": 1628701843,
    "isMonth": false,
    "isYear": false,
    "isHighlighted": false,
    "isRemoved": false,
    "slugs": [
      "hr",
      "rabota",
      "yandeks",
      "whiterussianstudio"
    ],
    "awards": []
  },
  {
    "id": 979,
    "title": "4 истории про то, что мы любим",
    "caption": "4 истории про то, что мы любим\nhttps://4stories.apokrif.media/\n\n#спецпроект #pixeljamstudio",
    "image": "data/images/979.jpg",
    "tags": [
      "спецпроект",
      "pixeljamstudio"
    ],
    "url": "https://4stories.apokrif.media/",
    "date": 1628276266,
    "isMonth": false,
    "isYear": false,
    "isHighlighted": false,
    "isRemoved": false,
    "slugs": [
      "spetsproekt",
      "pixeljamstudio"
    ],
    "awards": []
  }
]