[
  {
    "id": 255,
    "title": "Volt for Drive",
    "image": "data/images/255.jpg",
    "tags": [
      "сервис",
      "технологии",
      "бизнес",
      "redcollar"
    ],
    "url": "https://v4d.ru/",
    "date": 1533204018,
    "edit_date": 1583185435,
    "isHighlighted": false,
    "isRemoved": false,
    "slugs": [
      "servis",
      "tekhnologii",
      "biznes",
      "redcollar"
    ]
  },
  {
    "id": 190,
    "title": "Decta",
    "image": "data/images/190.jpg",
    "tags": [
      "финансы",
      "услуги",
      "технологии"
    ],
    "url": "https://decta.com/ru",
    "date": 1527674411,
    "edit_date": 1583185536,
    "isHighlighted": false,
    "isRemoved": false,
    "slugs": [
      "finansi",
      "uslugi",
      "tekhnologii"
    ]
  },
  {
    "id": 173,
    "title": "Хайтек",
    "image": "data/images/173.jpg",
    "tags": [
      "медиа",
      "новости",
      "технологии"
    ],
    "url": "https://hightech.fm/",
    "date": 1526205609,
    "edit_date": 1583185536,
    "isHighlighted": false,
    "isRemoved": false,
    "slugs": [
      "media",
      "novosti",
      "tekhnologii"
    ]
  }
]