[
  {
    "id": 984,
    "title": "Агентство комплексного интернет-маркетинга Wemakefab",
    "caption": "Агентство комплексного интернет-маркетинга Wemakefab\nhttps://wemakefab.ru/\n\n#портфолио #агентство  #lagutalaguta\nСпасибо за ссылку @masterlobster",
    "image": "data/images/984.jpg",
    "tags": [
      "портфолио",
      "агентство",
      "lagutalaguta"
    ],
    "url": "https://wemakefab.ru/",
    "date": 1629624600,
    "isMonth": false,
    "isYear": false,
    "isHighlighted": false,
    "isRemoved": false,
    "slugs": [
      "portfolio",
      "agentstvo",
      "lagutalaguta"
    ],
    "awards": []
  }
]